setup.py
myfirstpip/__init__.py
myfirstpip/hello.py
myfirstpip/myfirstpip.py
myfirstpip.egg-info/PKG-INFO
myfirstpip.egg-info/SOURCES.txt
myfirstpip.egg-info/dependency_links.txt
myfirstpip.egg-info/top_level.txt