Metadata-Version: 1.0
Name: myfirstpip
Version: 0.0.6
Summary: my first pip
Home-page: http://xiaohhhh.github.io/
Author: xiaohhhh
Author-email: xiaohhhh@gmail.com
License: MIT Licence
Keywords: pip
Platform: any
